{
    "header": {
        "id":"1",
        "version": "1",
        "created_by": "some_device-IMX18ID#1",
        "createdTime": "2021-10-04T14:00:00Z",
        "message_Type": "live_data"
    },
    "payload": {
        "insert": [
            {
                "fqn": "Ligeia.Inkai.CAT-1.pump 151/1.vibration_x",
                "vqts": [
                    {
                        "v": "325.0",
                        "q": 192,
                        "t": "2021-10-04T14:00:00Z"
                    }
                ]
            }
        ]
    }
}